Workbook

Sheet Material Details
A1: DATE | B1: CATEGORY | C1: COMPANY | D1: DEALER | E1: QTY | F1: MEASURING IN | G1: RATE | H1: TOTAL BILL AMOUNT
A2: 46055 | B2: STEEL | C2: VIZAG | D2: AK STEELS | E2: 1685 | F2: KG | H2: 133120
A3: 46056 | B3: STEEL | C3: VIZAG | D3: AK STEELS | E3: 880 | F3: KG | H3: 66200
A4: 46057 | B4: M-SAND | D4: KRISHNA | E4: 4 | F4: UNITS | G4: 4750 | H4: =Table1[[#This Row],[QTY]]*Table1[[#This Row],[RATE]] -> 19000
A5: 46057 | B5: 40 MM METAL | D5: KRISHNA | E5: 2 | F5: UNITS | G5: 4500 | H5: =Table1[[#This Row],[QTY]]*Table1[[#This Row],[RATE]] -> 9000
A6: 46057 | B6: CEMENT | C6: RAMCO | D6: PALANI MURUGAN | E6: 60 | F6: BAGS | G6: 290 | H6: =Table1[[#This Row],[QTY]]*Table1[[#This Row],[RATE]] -> 17400
A7: 46066 | B7: CEMENT | C7: RAMCO | D7: PALANI MURUGAN | E7: 120 | F7: BAGS | G7: 290 | H7: =Table1[[#This Row],[QTY]]*Table1[[#This Row],[RATE]] -> 34800
A8: 46066 | B8: M-SAND | D8: KRISHNA | E8: 8 | F8: UNITS | G8: 4750 | H8: =Table1[[#This Row],[QTY]]*Table1[[#This Row],[RATE]] -> 38000
A9: 46066 | B9: 20 MM JALLY | D9: KRISHNA | E9: 12 | F9: UNITS | G9: 4125 | H9: =Table1[[#This Row],[QTY]]*Table1[[#This Row],[RATE]] -> 49500
A10: 46066 | B10: CEMENT | C10: RAMCO | D10: PALANI MURUGAN | E10: 50 | F10: BAGS | G10: 290 | H10: =Table1[[#This Row],[QTY]]*Table1[[#This Row],[RATE]] -> 14500
A11: 46076 | B11: BRICK-FLYASH | D11: SV TRADERS | E11: 3000 | F11: NOS | G11: 7.5 | H11: =Table1[[#This Row],[QTY]]*Table1[[#This Row],[RATE]] -> 22500
A12: 46077 | B12: STEEL | C12: VIZAG | D12: AK STEELS | E12: 786 | H12: 61000
A13: 46080 | B13: STEEL | C13: VIZAG | D13: AK STEELS | E13: 359 | H13: 29190
A14: 46084 | B14: M-SAND | D14: KRISHNA | E14: 4 | F14: UNITS | G14: 4750 | H14: =Table1[[#This Row],[QTY]]*Table1[[#This Row],[RATE]] -> 19000
A15: 46084 | B15: 20 MM JALLY | D15: KRISHNA | E15: 4 | F15: UNITS | G15: 4125 | H15: =Table1[[#This Row],[QTY]]*Table1[[#This Row],[RATE]] -> 16500
A16: 46084 | B16: CEMENT | C16: RAMCO | D16: PALANI MURUGAN | E16: 50 | F16: BAGS | G16: 290 | H16: =Table1[[#This Row],[QTY]]*Table1[[#This Row],[RATE]] -> 14500
A17: 46085 | B17: BRICK | C17: ACB | D17: VEL BRICKS | E17: 3000 | F17: NOS | G17: 12 | H17: =Table1[[#This Row],[QTY]]*Table1[[#This Row],[RATE]] -> 36000
A18: 46088 | B18: CEMENT | C18: RAMCO | D18: PALANI MURUGAN | E18: 50 | F18: BAGS | G18: 290 | H18: =Table1[[#This Row],[QTY]]*Table1[[#This Row],[RATE]] -> 14500
A19: 46091 | B19: P-SAND | D19: KRISHNA | E19: 2 | F19: UNITS | G19: 6000 | H19: =Table1[[#This Row],[QTY]]*Table1[[#This Row],[RATE]] -> 12000
A20: 46101 | B20: STEEL | C20: VIZAG | D20: AK STEELS | H20: 45630
A21: 46102 | B21: M-SAND | D21: KRISHNA | E21: 4 | F21: UNITS | G21: 4750 | H21: =Table1[[#This Row],[QTY]]*Table1[[#This Row],[RATE]] -> 19000
A22: 46102 | B22: 40 MM METAL | D22: KRISHNA | E22: 4 | F22: UNITS | G22: 4125 | H22: =Table1[[#This Row],[QTY]]*Table1[[#This Row],[RATE]] -> 16500
A23: 46102 | B23: CEMENT | D23: CHAKRA TRADERS | E23: 50 | F23: BAGS | G23: 290 | H23: =Table1[[#This Row],[QTY]]*Table1[[#This Row],[RATE]] -> 14500
A24: 46107 | B24: BRICK-FLYASH | D24: AMARUN FLYASH | E24: 6000 | F24: NOS | G24: 8 | H24: =Table1[[#This Row],[QTY]]*Table1[[#This Row],[RATE]] -> 48000
A25: 46111 | B25: CEMENT | C25: RAMCO | D25: CHAKRA TRADERS | E25: 50 | F25: BAGS | G25: 290 | H25: =Table1[[#This Row],[QTY]]*Table1[[#This Row],[RATE]] -> 14500
A26: 46112 | B26: 20 MM JALLY | D26: KRISHNA | E26: 4 | F26: UNITS | G26: 4125 | H26: =Table1[[#This Row],[QTY]]*Table1[[#This Row],[RATE]] -> 16500
A27: 46113 | B27: STEEL | C27: VIZAG | D27: AK STEELS | E27: 736 | F27: KG | G27: 83.55 | H27: 61500
A28: 46120 | B28: BRICK | D28: VEL BRICKS | E28: -1600 | F28: NOS | G28: 12 | H28: =Table1[[#This Row],[QTY]]*Table1[[#This Row],[RATE]] -> -19200
A29: 46133 | B29: M-SAND | D29: KRISHNA | E29: 4 | F29: UNITS | G29: 4750 | H29: =Table1[[#This Row],[RATE]]*Table1[[#This Row],[QTY]] -> 19000
A30: 46133 | B30: STEEL | C30: VIZAG | D30: AK STEELS | E30: 1706 | F30: KG | H30: 136170
A31: 46142 | B31: STEEL | C31: DURGA | D31: LOCAL | E31: 46.6 | F31: KG | G31: 70 | H31: 3270
A32: 46143 | B32: STEEL | C32: VIZAG | D32: AK STEELS | E32: 464 | F32: KG | H32: 39420
A33: 46144 | B33: ELECTRICAL | D33: RAMDEV HARDWARES | H33: 10837
A34: 46146 | B34: CEMENT | C34: RAMCO | D34: CHAKRA TRADERS | E34: 150 | F34: BAGS | G34: 335 | H34: =Table1[[#This Row],[QTY]]*Table1[[#This Row],[RATE]] -> 50250
A35: 46146 | B35: M-SAND | D35: KRISHNA | E35: 4 | F35: UNITS | G35: 4750 | H35: =Table1[[#This Row],[QTY]]*Table1[[#This Row],[RATE]] -> 19000
A36: 46146 | B36: 20 MM JALLY | D36: KRISHNA | E36: 4 | F36: UNITS | G36: 4125 | H36: =Table1[[#This Row],[QTY]]*Table1[[#This Row],[RATE]] -> 16500
A37: 46158 | B37: BRICK-FLYASH | D37: SV TRADERS | E37: 1500 | F37: NOS | G37: 8.5 | H37: =Table1[[#This Row],[QTY]]*Table1[[#This Row],[RATE]] -> 12750
A38: 46174 | B38: BRICK-FLYASH | D38: AMARUN FLYASH | E38: 3000 | F38: NOS | G38: 8.3 | H38: =Table1[[#This Row],[QTY]]*Table1[[#This Row],[RATE]] -> 24900
A39: 46146 | B39: STEEL | C39: VIZAG | D39: AK STEELS | E39: 1420 | F39: KG | H39: 107070
A40: 46179 | B40: STEEL | C40: VIZAG | D40: AK STEELS | E40: 209 | F40: KG | H40: 16640

Sheet Reference Table
A1: CATEGORY | B1: MEASURING IN | C1: RATE
A2: M-SAND | B2: UNITS | C2: 5125
A3: 40 MM METAL | B3: UNITS | C3: 4450
A4: BRICK | B4: NOS | C4: 7.2
A5: 20 MM JALLY | B5: UNITS | C5: 4450
A6: P-SAND | B6: UNITS | C6: 5950
A7: GRAVEL | B7: UNITS | C7: 2200
A8: CEMENT | B8: BAGS
A9: STEEL | B9: KG
A10: ELECTRICAL
A11: BRICK-FLYASH

Sheet Materials Total QTY
A1: MATERIALS | B1: QTY | C1: MEASURING IN | D1: TOTAL AMOUNT
A2: {=_xlfn.UNIQUE('Material Details'!B2:B1010)} -> STEEL | B2: =SUMIF('Material Details'!B2:B1010,A2,'Material Details'!E2:E1010) -> 8291.6 | C2: KG | D2: =SUMIF('Material Details'!B2:B1010,A2,'Material Details'!H2:H1010) -> 699210
A3: M-SAND | B3: =SUMIF('Material Details'!B3:B1011,A3,'Material Details'!E3:E1011) -> 28 | C3: UNITS | D3: =SUMIF('Material Details'!B3:B1011,A3,'Material Details'!H3:H1011) -> 133000
A4: 40 MM METAL | B4: =SUMIF('Material Details'!B4:B1012,A4,'Material Details'!E4:E1012) -> 6 | C4: UNITS | D4: =SUMIF('Material Details'!B4:B1012,A4,'Material Details'!H4:H1012) -> 25500
A5: CEMENT | B5: =SUMIF('Material Details'!B5:B1013,A5,'Material Details'!E5:E1013) -> 580 | C5: BAGS | D5: =SUMIF('Material Details'!B5:B1013,A5,'Material Details'!H5:H1013) -> 174950
A6: 20 MM JALLY | B6: =SUMIF('Material Details'!B6:B1014,A6,'Material Details'!E6:E1014) -> 24 | C6: UNITS | D6: =SUMIF('Material Details'!B6:B1014,A6,'Material Details'!H6:H1014) -> 99000
A7: BRICK-FLYASH | B7: =SUMIF('Material Details'!B7:B1015,A7,'Material Details'!E7:E1015) -> 13500 | C7: UNITS | D7: =SUMIF('Material Details'!B7:B1015,A7,'Material Details'!H7:H1015) -> 108150
A8: BRICK | B8: =SUMIF('Material Details'!B9:B1016,A8,'Material Details'!E9:E1016) -> 1400 | C8: UNITS | D8: =SUMIF('Material Details'!B8:B1016,A8,'Material Details'!H8:H1016) -> 16800
A9: P-SAND | B9: =SUMIF('Material Details'!B10:B1017,A9,'Material Details'!E10:E1017) -> 2 | C9: UNITS | D9: =SUMIF('Material Details'!B9:B1017,A9,'Material Details'!H9:H1017) -> 12000
A10: ELECTRICAL | B10: =SUMIF('Material Details'!B11:B1018,A10,'Material Details'!E11:E1018) -> 0 | C10: UNITS | D10: =SUMIF('Material Details'!B10:B1018,A10,'Material Details'!H10:H1018) -> 10837
A11: 0

Sheet Vendor Balance Sheet
A1: VENDOR NAME | B1: TOTAL BILL AMOUNT | C1: TOTAL AMOUNT PAID | D1: BALANCE AMOUNT
A2: {=_xlfn.UNIQUE('Material Details'!D2:D1010)} -> AK STEELS | B2: =SUMIF('Material Details'!D2:D1010,A2,'Material Details'!H2:H1010) -> 695940 | C2: =SUMIF('Payment Details'!B2:B991,'Vendor Balance Sheet'!A2,'Payment Details'!C2:C991) -> 565000 | D2: =B2-C2 -> 130940
A3: KRISHNA | B3: =SUMIF('Material Details'!D2:D1010,A3,'Material Details'!H2:H1010) -> 269500 | C3: =SUMIF('Payment Details'!B2:B992,'Vendor Balance Sheet'!A3,'Payment Details'!C2:C992) -> 255000 | D3: =B3-C3 -> 14500
A4: PALANI MURUGAN | B4: =SUMIF('Material Details'!D3:D1011,A4,'Material Details'!H3:H1011) -> 95700 | C4: =SUMIF('Payment Details'!B2:B991,'Vendor Balance Sheet'!A4,'Payment Details'!C2:C991) -> 95700 | D4: =B4-C4 -> 0
A5: SV TRADERS | B5: =SUMIF('Material Details'!D4:D1012,A5,'Material Details'!H4:H1012) -> 35250 | C5: =SUMIF('Payment Details'!B2:B992,'Vendor Balance Sheet'!A5,'Payment Details'!C2:C992) -> 35250 | D5: =B5-C5 -> 0
A6: VEL BRICKS | B6: =SUMIF('Material Details'!D5:D1013,A6,'Material Details'!H5:H1013) -> 16800 | C6: =SUMIF('Payment Details'!B3:B993,'Vendor Balance Sheet'!A6,'Payment Details'!C3:C993) -> 16800 | D6: =B6-C6 -> 0
A7: CHAKRA TRADERS | B7: =SUMIF('Material Details'!D6:D1014,A7,'Material Details'!H6:H1014) -> 79250 | C7: =SUMIF('Payment Details'!B4:B994,'Vendor Balance Sheet'!A7,'Payment Details'!C4:C994) -> 79250 | D7: =B7-C7 -> 0
A8: AMARUN FLYASH | B8: =SUMIF('Material Details'!D7:D1015,A8,'Material Details'!H7:H1015) -> 72900 | C8: =SUMIF('Payment Details'!B5:B995,'Vendor Balance Sheet'!A8,'Payment Details'!C5:C995) -> 72900 | D8: =B8-C8 -> 0
A9: LOCAL | B9: =SUMIF('Material Details'!D8:D1016,A9,'Material Details'!H8:H1016) -> 3270 | C9: =SUMIF('Payment Details'!B6:B996,'Vendor Balance Sheet'!A9,'Payment Details'!C6:C996) -> 0 | D9: =B9-C9 -> 3270
A10: RAMDEV HARDWARES | B10: =SUMIF('Material Details'!D9:D1017,A10,'Material Details'!H9:H1017) -> 10837 | C10: =SUMIF('Payment Details'!B7:B997,'Vendor Balance Sheet'!A10,'Payment Details'!C7:C997) -> 8000 | D10: =B10-C10 -> 2837
A11: 0
D13: =SUM(D2:D12) -> 151547

Sheet Payment Details
A1: DATE | B1: VENDOR NAME | C1: AMOUNT PAID | D1: MODE OF PAYMENT | E1: GST BILL | F1: DESCRPTION
A2: 46060 | B2: AK STEELS | C2: 195000 | D2: CASH | E2: YES | F2: Steel Part Payment
A3: 46060 | B3: KRISHNA | C3: 20000 | D3: CASH | E3: NO | F3: Part Payment
A4: 46067 | B4: KRISHNA | C4: 50000 | D4: CASH | E4: NO | F4: Part Payment
A5: 46071 | B5: PALANI MURUGAN | C5: 50000 | D5: CASH | E5: YES | F5: Part Payment
A6: 46081 | B6: SV TRADERS | C6: 20000 | D6: CASH | E6: NO | F6: Part Payment
A7: 46088 | B7: PALANI MURUGAN | C7: 20000 | D7: CASH | E7: YES | F7: Part Payment
A8: 46088 | B8: KRISHNA | C8: 30000 | D8: CASH | E8: NO | F8: Part Payment
A9: 46088 | B9: VEL BRICKS | C9: 36000 | D9: CASH | E9: NO | F9: Brick Payment
A10: 46088 | B10: AK STEELS | C10: 50000 | D10: CASH | E10: YES | F10: Steel Part Payment
A11: 46102 | B11: KRISHNA | C11: 50000 | D11: CASH | E11: NO | F11: Part Payment
A12: 46102 | B12: SV TRADERS | C12: 2500 | D12: CASH | E12: NO | F12: Pending Amount
A13: 46102 | B13: CHAKRA TRADERS | C13: 8000 | D13: CASH | E13: YES | F13: Cement Part Paymnet
... A33: 46179 | B33: AMARUN FLYASH | C33: 24900 | D33: CASH | E33: NO | F33: Full amount
